tinymovr/__init__.py
tinymovr/bus_manager.py
tinymovr/bus_router.py
tinymovr/channel.py
tinymovr/cli.py
tinymovr/constants.py
tinymovr/device_discovery.py
tinymovr/dfu.py
tinymovr/codec/__init__.py
tinymovr/codec/codec.py
tinymovr/config/__init__.py
tinymovr/config/config.py
tinymovr/gui/__init__.py
tinymovr/gui/gui.py
tinymovr/gui/helpers.py
tinymovr/gui/widgets.py
tinymovr/gui/window.py
tinymovr/gui/worker.py
tinymovr/resources/icons/app_icon.png
tinymovr/resources/icons/call.png
tinymovr/resources/icons/call@2x.png
tinymovr/resources/icons/call_dark.png
tinymovr/resources/icons/call_dark@2x.png
tinymovr/resources/icons/empty.png
tinymovr/resources/icons/empty@2x.png
tinymovr/resources/icons/empty_dark.png
tinymovr/resources/icons/empty_dark@2x.png
tinymovr/specs/dfu_1_0_x.yaml
tinymovr/specs/dfu_1_1_x.yaml
tinymovr/specs/tinymovr_1_3_x.yaml
tinymovr/specs/tinymovr_1_4_x.yaml
tinymovr/specs/tinymovr_1_5_x.yaml
tinymovr/specs/tinymovr_1_6_x.yaml
tinymovr/specs/tinymovr_2_0_x.yaml
tinymovr/specs/tinymovr_2_1_x.yaml
tinymovr/specs/tinymovr_2_3_x.yaml
tinymovr-2.3.4.dist-info/METADATA
tinymovr-2.3.4.dist-info/WHEEL
tinymovr-2.3.4.dist-info/entry_points.txt
tinymovr-2.3.4.dist-info/top_level.txt
tinymovr-2.3.4.dist-info/RECORD
