Metadata-Version: 2.4
Name: tinymovr
Version: 2.3.4
Summary: Tinymovr Studio
Home-page: https://github.com/yconst/Tinymovr
Author: Yannis Chatzikonstantinou
Author-email: info@tinymovr.com
Classifier: Programming Language :: Python :: 3
Classifier: License :: OSI Approved :: GNU General Public License v3 or later (GPLv3+)
Classifier: Operating System :: OS Independent
Requires-Python: >=3.9
Requires-Dist: ipython
Requires-Dist: importlib_resources
Requires-Dist: python-can
Requires-Dist: python-can-canine
Requires-Dist: python-can-slcan_disco
Requires-Dist: avlos>=0.6.6
Requires-Dist: pyserial
Requires-Dist: pyusb
Requires-Dist: pyyaml
Requires-Dist: docopt
Requires-Dist: flatten-dict
Requires-Dist: pint
Requires-Dist: pretty_errors
Provides-Extra: gui
Requires-Dist: pyside6; extra == "gui"
Requires-Dist: pyqtgraph>=0.13.3; extra == "gui"
Dynamic: author
Dynamic: author-email
Dynamic: classifier
Dynamic: description
Dynamic: description-content-type
Dynamic: home-page
Dynamic: provides-extra
Dynamic: requires-dist
Dynamic: requires-python
Dynamic: summary
